pyreqver/__init__.py
pyreqver/__version__.py
pyreqver/main.py
pyreqver-0.1.0.dist-info/licenses/LICENSE
pyreqver-0.1.0.dist-info/METADATA
pyreqver-0.1.0.dist-info/WHEEL
pyreqver-0.1.0.dist-info/entry_points.txt
pyreqver-0.1.0.dist-info/top_level.txt
pyreqver-0.1.0.dist-info/RECORD
