Metadata-Version: 2.4
Name: pyreqver
Version: 0.1.0
Summary:  A command-line tool that helps you find Python versions that support all libraries in your requirements.txt file
Home-page: https://github.com/evanstellun/pyreqver
Author: Evanstellun
Author-email: niweilun@outlook.com
License: MIT
Classifier: License :: OSI Approved :: MIT License
Classifier: Programming Language :: Python
Classifier: Programming Language :: Python :: 3
Classifier: Programming Language :: Python :: 3.6
Classifier: Programming Language :: Python :: Implementation :: CPython
Classifier: Programming Language :: Python :: Implementation :: PyPy
Requires-Python: >=3.6.0
License-File: LICENSE
Requires-Dist: requests
Requires-Dist: packaging
Dynamic: author
Dynamic: author-email
Dynamic: classifier
Dynamic: description
Dynamic: description-content-type
Dynamic: home-page
Dynamic: license
Dynamic: license-file
Dynamic: requires-dist
Dynamic: requires-python
Dynamic: summary
